citation_utils/__init__.py
citation_utils/citation.py
citation_utils/document.py
citation_utils/special.py
citation_utils/dockets/__init__.py
citation_utils/dockets/constructed_ac.py
citation_utils/dockets/constructed_am.py
citation_utils/dockets/constructed_bm.py
citation_utils/dockets/constructed_gr.py
citation_utils/dockets/constructed_jib.py
citation_utils/dockets/constructed_oca.py
citation_utils/dockets/constructed_pet.py
citation_utils/dockets/constructed_udk.py
citation_utils/dockets/models/__init__.py
citation_utils/dockets/models/constructor.py
citation_utils/dockets/models/docket_category.py
citation_utils/dockets/models/docket_citation.py
citation_utils/dockets/models/docket_model.py
citation_utils/dockets/models/docket_rules.py
citation_utils/dockets/models/gr_clean.py
citation_utils/dockets/models/misc/__init__.py
citation_utils/dockets/models/misc/extra.py
citation_utils/dockets/models/misc/num.py
citation_utils/dockets/models/misc/x.py
citation_utils-0.5.0.dist-info/licenses/LICENSE
citation_utils-0.5.0.dist-info/METADATA
citation_utils-0.5.0.dist-info/WHEEL
citation_utils-0.5.0.dist-info/top_level.txt
citation_utils-0.5.0.dist-info/RECORD
