Metadata-Version: 2.4
Name: citation-utils
Version: 0.5.0
Summary: Pattern matching Philippine Supreme Court citations.
Requires-Python: >=3.13
License-File: LICENSE
Requires-Dist: citation-report>=0.2.0
Dynamic: license-file
